libname/Systematica.py
libname/__init__.py
systematica-0.0.3.dist-info/METADATA
systematica-0.0.3.dist-info/WHEEL
systematica-0.0.3.dist-info/top_level.txt
systematica-0.0.3.dist-info/RECORD
