Metadata-Version: 2.1
Name: systematica
Version: 0.0.3
Summary: Simple Simulator for Computer Vision
Author: TucuAI (Tucudean Adrian-Ionut)
Author-email: <Tucudean.Adrian.Ionut@outlook.com>
Keywords: python,simulator,computer vision,advanced driving,camera stream,camera handler
Classifier: Development Status :: 1 - Planning
Classifier: Intended Audience :: Developers
Classifier: Programming Language :: Python :: 3
Classifier: Operating System :: Unix
Classifier: Operating System :: MacOS :: MacOS X
Classifier: Operating System :: Microsoft :: Windows
Requires-Dist: opencv-python
Requires-Dist: pygame
